covidsource/__init__.py
covidsource/transformers/__init__.py
covidsource/transformers/columns_base.py
covidsource/transformers/rows_base.py
covidsource/utils/__init__.py
covidsource/utils/common_func.py
covidsource/utils/config.py
covidsource/utils/dataload.py
covidsource/utils/display_func.py
covidsource/utils/expansion_func.py
criteria_etl-0.1.0.dist-info/LICENSE
criteria_etl-0.1.0.dist-info/METADATA
criteria_etl-0.1.0.dist-info/WHEEL
criteria_etl-0.1.0.dist-info/top_level.txt
criteria_etl-0.1.0.dist-info/RECORD
