Metadata-Version: 2.1
Name: criteria-etl
Version: 0.1.0
Summary: A library for Criteria related data wrangling.
Home-page: https://github.com/prosper-ia/covid-response-source
Author: Prosperia Social
Author-email: developers.etl@prosperia.ai
License: UNKNOWN
Platform: UNKNOWN
Classifier: Programming Language :: Python :: 3
Classifier: License :: OSI Approved :: MIT License
Classifier: Operating System :: OS Independent
Requires-Python: >=3.7
Requires-Dist: pandas (>=1)
Requires-Dist: scikit-learn
